playwright_nodejs/__init__.py
playwright_nodejs/node.py
playwright_nodejs-0.0.2.dist-info/LICENSE
playwright_nodejs-0.0.2.dist-info/METADATA
playwright_nodejs-0.0.2.dist-info/WHEEL
playwright_nodejs-0.0.2.dist-info/top_level.txt
playwright_nodejs-0.0.2.dist-info/RECORD
