Metadata-Version: 2.1
Name: playwright-nodejs
Version: 0.0.2
Summary: There is a Node.js environment in playwright, why not just use it?
Author-email: Shi Yz <yz.shi@outlook.com>
Project-URL: Homepage, https://github.com/lordqyxz/playwright_nodejs
Project-URL: Bug Tracker, https://github.com/lordqyxz/playwright_nodejs/issues
Classifier: Programming Language :: Python :: 3
Classifier: License :: OSI Approved :: MIT License
Classifier: Operating System :: OS Independent
Requires-Python: >=3.8
License-File: LICENSE
